inline_text_fields_component/__init__.py
inline_text_fields_component/frontend/dist/index.html
inline_text_fields_component/frontend/dist/assets/index.js
streamlit_inline_text_fields-0.1.5.dist-info/licenses/LICENSE
streamlit_inline_text_fields-0.1.5.dist-info/METADATA
streamlit_inline_text_fields-0.1.5.dist-info/WHEEL
streamlit_inline_text_fields-0.1.5.dist-info/top_level.txt
streamlit_inline_text_fields-0.1.5.dist-info/RECORD
