Metadata-Version: 2.4
Name: streamlit-inline-text-fields
Version: 0.1.5
Summary: Streamlit component for inline-text-fields
Home-page: https://github.com/ffhammer/streamlit-inline-text-fields
Author: Felix Hammer
Author-email: fhammer@uos.de
Requires-Python: >=3.8
License-File: LICENSE
Requires-Dist: streamlit>=1.0
Dynamic: author
Dynamic: author-email
Dynamic: description
Dynamic: description-content-type
Dynamic: home-page
Dynamic: license-file
Dynamic: requires-dist
Dynamic: requires-python
Dynamic: summary
